{"trial_id": "07", "hyperparameters": {"space": [{"class_name": "Choice", "config": {"name": "n_layers", "default": 1, "conditions": [], "values": [1, 2, 3], "ordered": true}}, {"class_name": "Choice", "config": {"name": "rate", "default": 0.25, "conditions": [], "values": [0.25, 0.4, 0.5], "ordered": true}}, {"class_name": "Choice", "config": {"name": "units", "default": 128, "conditions": [], "values": [128, 256, 512], "ordered": true}}, {"class_name": "Choice", "config": {"name": "lr", "default": 0.001, "conditions": [], "values": [0.001, 0.0001, 1e-05], "ordered": true}}], "values": {"n_layers": 3, "rate": 0.25, "units": 128, "lr": 0.001}}, "metrics": {"metrics": {"accuracy": {"direction": "max", "observations": [{"value": [0.9291836619377136], "step": 9}]}, "loss": {"direction": "min", "observations": [{"value": [0.20064575970172882], "step": 9}]}, "val_accuracy": {"direction": "max", "observations": [{"value": [0.8628571629524231], "step": 9}]}, "val_loss": {"direction": "min", "observations": [{"value": [0.4222346246242523], "step": 9}]}}}, "score": 0.4222346246242523, "best_step": 9, "status": "COMPLETED", "message": null}